appzoo/__init__.py
appzoo/app.py
appzoo/app_run.py
appzoo/gunicorn.conf.py
appzoo/main.py
appzoo/req.py
appzoo/test.py
appzoo/apps_fastapi/__init__.py
appzoo/apps_fastapi/ann_search_app.py
appzoo/apps_fastapi/appzoo_demo.py
appzoo/apps_fastapi/common_app.py
appzoo/apps_fastapi/demo.py
appzoo/apps_fastapi/feishu_bot_app.py
appzoo/apps_fastapi/gen_synonyms.py
appzoo/apps_fastapi/image.png
appzoo/apps_fastapi/lite_app.py
appzoo/apps_fastapi/mongo_cache.py
appzoo/apps_fastapi/mongo_item.py
appzoo/apps_fastapi/nh_choice_model.py
appzoo/apps_fastapi/ocr_app.py
appzoo/apps_fastapi/ocr_app_.py
appzoo/apps_fastapi/raw_app.py
appzoo/apps_fastapi/simbert_app.py
appzoo/apps_fastapi/test.py
appzoo/apps_fastapi/user_ann.py
appzoo/apps_fastapi/wecom_callback.py
appzoo/apps_fastapi/wecom_callback_.py
appzoo/apps_fastapi/wecom_callback_fastapi.py
appzoo/apps_fastapi/test/__init__.py
appzoo/apps_fastapi/test/app.py
appzoo/apps_fastapi/test/demo.py
appzoo/apps_fastapi/test/hun.py
appzoo/apps_gradio/2_.png
appzoo/apps_gradio/__init__.py
appzoo/apps_gradio/demo.py
appzoo/apps_gradio/x.py
appzoo/apps_gradio/flagged/log.csv
appzoo/apps_gradio/flagged/name/0.png
appzoo/apps_gradio/flagged/name/1.png
appzoo/apps_gradio/flagged/name/2.png
appzoo/apps_gradio/gradio_cached_examples/17/log.csv
appzoo/apps_gradio/gradio_cached_examples/18/log.csv
appzoo/apps_gui/README.md
appzoo/apps_gui/__init__.py
appzoo/apps_gui/demo.py
appzoo/apps_gui/gooey_gui.py
appzoo/apps_pywebio/__init__.py
appzoo/apps_pywebio/demo.py
appzoo/apps_pywebio/demo1.py
appzoo/apps_rpc/RpcApp.py
appzoo/apps_rpc/__init__.py
appzoo/apps_rpc/client.py
appzoo/apps_rpc/pingpong.thrift
appzoo/apps_rpc/server.py
appzoo/apps_streamlit/README.md
appzoo/apps_streamlit/__init__.py
appzoo/apps_streamlit/demo.py
appzoo/apps_streamlit/demo_app.py
appzoo/apps_streamlit/display_data.py
appzoo/apps_streamlit/display_request.py
appzoo/apps_streamlit/example.py
appzoo/apps_streamlit/nlpzoo_app.py
appzoo/apps_streamlit/ocr_app.py
AppZoo-2023.4.25.19.12.44.dist-info/LICENSE
AppZoo-2023.4.25.19.12.44.dist-info/METADATA
AppZoo-2023.4.25.19.12.44.dist-info/WHEEL
AppZoo-2023.4.25.19.12.44.dist-info/entry_points.txt
AppZoo-2023.4.25.19.12.44.dist-info/top_level.txt
AppZoo-2023.4.25.19.12.44.dist-info/RECORD
