Metadata-Version: 2.1
Name: AppZoo
Version: 2023.4.25.19.12.44
Summary: description
Home-page: https://github.com/yuanjie-ai/AppZoo
Author: yuanjie
Author-email: 313303303@qq.com
Maintainer: yuanjie
Maintainer-email: 313303303@qq.com
License: MIT License
Keywords: utils
Platform: all
Classifier: Operating System :: OS Independent
Classifier: Intended Audience :: Developers
Classifier: License :: OSI Approved :: MIT License
Classifier: Programming Language :: Python
Classifier: Programming Language :: Python :: Implementation
Requires-Python: >=3.6
License-File: LICENSE
Requires-Dist: meutils
Requires-Dist: fastapi[all]
Provides-Extra: all
